{
  "pdb_id": "1EC6",
  "summary": {
    "total_canonical_cww": 8,
    "true_positives": 7,
    "false_negatives": 1,
    "false_positives": 0,
    "sensitivity": 0.875,
    "precision": 1.0
  },
  "false_negatives": [
    {
      "res_id1": "C-G-3",
      "res_id2": "C-C-18",
      "sequence": "GC",
      "our_prediction": "tWW",
      "dssr_class": "cWW",
      "saenger": "19-XIX",
      "reasons": [
        "wrong_atoms",
        "extra_hbonds"
      ],
      "hbond_diagnostics": {
        "expected_hbonds": [
          {
            "donor_atom": "N1",
            "acceptor_atom": "N3",
            "source": "canonical"
          },
          {
            "donor_atom": "N2",
            "acceptor_atom": "O2",
            "source": "canonical"
          },
          {
            "donor_atom": "O6",
            "acceptor_atom": "N4",
            "source": "canonical"
          }
        ],
        "found_hbonds": [
          {
            "donor_atom": "N2",
            "acceptor_atom": "O2",
            "distance": 2.65,
            "context": "base_base",
            "h_slot": 1,
            "lp_slot": 0,
            "alignment": 0.87
          },
          {
            "donor_atom": "N1",
            "acceptor_atom": "N3",
            "distance": 2.8,
            "context": "base_base",
            "h_slot": 0,
            "lp_slot": 0,
            "alignment": 1.96
          },
          {
            "donor_atom": "N4",
            "acceptor_atom": "O6",
            "distance": 2.95,
            "context": "base_base",
            "h_slot": 1,
            "lp_slot": 0,
            "alignment": 0.99
          },
          {
            "donor_atom": "N2",
            "acceptor_atom": "N3",
            "distance": 3.05,
            "context": "base_base",
            "h_slot": 1,
            "lp_slot": 0,
            "alignment": 1.61
          }
        ],
        "missing_hbonds": [],
        "extra_hbonds": [
          {
            "donor_atom": "N2",
            "acceptor_atom": "N3",
            "distance": 3.05,
            "context": "base_base"
          }
        ],
        "wrong_atoms": {
          "N2->N3": "Expected N2->O2, got N2->N3"
        },
        "distance_issues": [],
        "overloaded_acceptors": []
      },
      "geometric_diagnostics": {
        "rmsd_cww": 0.2463779355391508,
        "rmsd_best": 0.2417694662743864,
        "best_lw": "tWW",
        "rmsd_gap": 0.004608469264764409,
        "interbase_angle": 19.458,
        "n1n9_distance": 8.883,
        "is_geometric_outlier": false
      }
    }
  ],
  "false_positives": []
}